finsignals/__init__.py
finsignals/indicators.py
finsignals/preprocessing.py
finsignals/utils.py
finsignals/visualization.py
finsignals-0.1.0.dist-info/licenses/LICENSE
finsignals-0.1.0.dist-info/METADATA
finsignals-0.1.0.dist-info/WHEEL
finsignals-0.1.0.dist-info/top_level.txt
finsignals-0.1.0.dist-info/RECORD
